LICENSE
README.md
setup.py
reformer/__init__.py
reformer/main.py
reformer/reform_dictionary.py
reformer_cil.egg-info/PKG-INFO
reformer_cil.egg-info/SOURCES.txt
reformer_cil.egg-info/dependency_links.txt
reformer_cil.egg-info/top_level.txt